COPYING
MANIFEST.in
README.rst
keccak.c
keccak.pyx
setup.py
test_keccak.py
vcversioner.py
version.txt
cykeccak.egg-info/PKG-INFO
cykeccak.egg-info/SOURCES.txt
cykeccak.egg-info/dependency_links.txt
cykeccak.egg-info/top_level.txt
src/AVR8-rotate64.h
src/AVR8-rotate64.s
src/Keccak-avr8-settings.h
src/Keccak-avr8-test.c
src/Keccak-avr8-util.h
src/Keccak-avr8-util.s
src/Keccak-avr8.c
src/Keccak-avr8.h
src/Keccak-compact-settings.h
src/Keccak-compact-test.c
src/Keccak-compact.c
src/Keccak-compact.h
src/Keccak-compact8-settings.h
src/Keccak-compact8-test.c
src/Keccak-compact8.c
src/Keccak-compact8.h
src/Keccak-crypto_hash-inplace-armgcc-ARMv7A-NEON.s
src/Keccak-inplace-minimal-test.c
src/Keccak-inplace-settings.h
src/Keccak-inplace-test.c
src/Keccak-inplace.c
src/Keccak-inplace32BI-armgcc-ARMv6M.s
src/Keccak-inplace32BI-armgcc-ARMv7A.s
src/Keccak-inplace32BI-armgcc-ARMv7M.s
src/Keccak-inplace32BI.c
src/Keccak-simple-settings.h
src/Keccak-simple-test.c
src/Keccak-simple.c
src/Keccak-simple32BI.c
src/KeccakDuplex.c
src/KeccakDuplex.h
src/KeccakF-1600-32-rvk.macros
src/KeccakF-1600-32-s1.macros
src/KeccakF-1600-32-s2.macros
src/KeccakF-1600-32.macros
src/KeccakF-1600-64.macros
src/KeccakF-1600-arm.c
src/KeccakF-1600-armcc.s
src/KeccakF-1600-armgcc.s
src/KeccakF-1600-avr8.c
src/KeccakF-1600-avr8asm-compact.s
src/KeccakF-1600-avr8asm-fast.s
src/KeccakF-1600-inplace-armgcc-ARMv7A-NEON.s
src/KeccakF-1600-int-set.h
src/KeccakF-1600-interface.h
src/KeccakF-1600-opt32-settings.h
src/KeccakF-1600-opt32.c
src/KeccakF-1600-opt64-settings.h
src/KeccakF-1600-opt64.c
src/KeccakF-1600-reference.c
src/KeccakF-1600-reference.h
src/KeccakF-1600-reference32BI.c
src/KeccakF-1600-simd128.macros
src/KeccakF-1600-simd64.macros
src/KeccakF-1600-unrolling.macros
src/KeccakF-1600-x86-64-asm.c
src/KeccakF-1600-x86-64-gas.s
src/KeccakF-1600-x86-64-shld-gas.s
src/KeccakF-1600-xop.macros
src/KeccakNISTInterface.c
src/KeccakNISTInterface.h
src/KeccakSponge.c
src/KeccakSponge.h
src/Keccakc1024-crypto_hash-inplace-armgcc-ARMv7A-NEON.s
src/Keccakc512-crypto_hash-inplace-armgcc-ARMv7A-NEON.s
src/brg_endian.h
src/crypto_hash.h
