Metadata-Version: 1.1
Name: cykeccak
Version: 0.13.2.2
Summary: Cython bindings to the Keccak sponge and SHA-3 functions
Home-page: https://github.com/habnabit/cykeccak
Author: Aaron Gallagher
Author-email: _@habnab.it
License: ISC
Platform: POSIX
Classifier: Development Status :: 3 - Alpha
Classifier: Intended Audience :: Developers
Classifier: License :: OSI Approved :: ISC License (ISCL)
Classifier: Operating System :: POSIX
Classifier: Programming Language :: Cython
Classifier: Programming Language :: C
Classifier: Programming Language :: Python :: 2
Classifier: Programming Language :: Python :: 2.6
Classifier: Programming Language :: Python :: 2.7
Classifier: Programming Language :: Python :: 3
Classifier: Programming Language :: Python :: 3.2
Classifier: Programming Language :: Python :: 3.3
Classifier: Topic :: Security :: Cryptography
